easysewer/Area.py
easysewer/Curve.py
easysewer/JsonHandler.py
easysewer/Link.py
easysewer/ModelAPI.py
easysewer/Node.py
easysewer/Options.py
easysewer/OutputAPI.py
easysewer/Rain.py
easysewer/SolverAPI.py
easysewer/UDM.py
easysewer/__init__.py
easysewer/utils.py
easysewer/libs/linux/flexible_ponding.so.esso
easysewer/libs/linux/swmm-output.so.esso
easysewer/libs/linux/swmm5.so.esso
easysewer/libs/win/flexible_ponding.dll.esdll
easysewer/libs/win/swmm-output.dll.esdll
easysewer/libs/win/swmm5.dll.esdll
easysewer-0.0.8.dist-info/METADATA
easysewer-0.0.8.dist-info/WHEEL
easysewer-0.0.8.dist-info/top_level.txt
easysewer-0.0.8.dist-info/RECORD
