Metadata-Version: 2.4
Name: easysewer
Version: 0.0.8
Summary: An urban drainage modeling toolkit
Author-email: Yiran Ji <yiranji@zju.edu.cn>
License-Expression: AGPL-3.0-only
Project-URL: Homepage, https://github.com/yourusername/easysewer
Project-URL: Documentation, https://github.com/yourusername/easysewer#readme
Classifier: Programming Language :: Python :: 3
Classifier: Operating System :: OS Independent
Requires-Python: >=3.10
